pythondata_cpu_cva5/__init__.py
pythondata_cpu_cva5/system_verilog/.gitlab-ci.yml
pythondata_cpu_cva5/system_verilog/LICENSE
pythondata_cpu_cva5/system_verilog/README.md
pythondata_cpu_cva5/system_verilog/core/addr_hash.sv
pythondata_cpu_cva5/system_verilog/core/alu_unit.sv
pythondata_cpu_cva5/system_verilog/core/amo_alu.sv
pythondata_cpu_cva5/system_verilog/core/avalon_master.sv
pythondata_cpu_cva5/system_verilog/core/axi_master.sv
pythondata_cpu_cva5/system_verilog/core/axi_to_arb.sv
pythondata_cpu_cva5/system_verilog/core/barrel_shifter.sv
pythondata_cpu_cva5/system_verilog/core/binary_occupancy.sv
pythondata_cpu_cva5/system_verilog/core/branch_comparator.sv
pythondata_cpu_cva5/system_verilog/core/branch_predictor.sv
pythondata_cpu_cva5/system_verilog/core/branch_predictor_ram.sv
pythondata_cpu_cva5/system_verilog/core/branch_unit.sv
pythondata_cpu_cva5/system_verilog/core/byte_en_BRAM.sv
pythondata_cpu_cva5/system_verilog/core/clz.sv
pythondata_cpu_cva5/system_verilog/core/csr_types.sv
pythondata_cpu_cva5/system_verilog/core/csr_unit.sv
pythondata_cpu_cva5/system_verilog/core/cva5.sv
pythondata_cpu_cva5/system_verilog/core/cva5_config.sv
pythondata_cpu_cva5/system_verilog/core/cva5_fifo.sv
pythondata_cpu_cva5/system_verilog/core/cva5_types.sv
pythondata_cpu_cva5/system_verilog/core/cycler.sv
pythondata_cpu_cva5/system_verilog/core/dcache.sv
pythondata_cpu_cva5/system_verilog/core/ddata_bank.sv
pythondata_cpu_cva5/system_verilog/core/decode_and_issue.sv
pythondata_cpu_cva5/system_verilog/core/div_core.sv
pythondata_cpu_cva5/system_verilog/core/div_unit.sv
pythondata_cpu_cva5/system_verilog/core/dtag_banks.sv
pythondata_cpu_cva5/system_verilog/core/external_interfaces.sv
pythondata_cpu_cva5/system_verilog/core/fetch.sv
pythondata_cpu_cva5/system_verilog/core/gc_unit.sv
pythondata_cpu_cva5/system_verilog/core/icache.sv
pythondata_cpu_cva5/system_verilog/core/illegal_instruction_checker.sv
pythondata_cpu_cva5-0.0.post649.dist-info/LICENSE
pythondata_cpu_cva5-0.0.post649.dist-info/METADATA
pythondata_cpu_cva5-0.0.post649.dist-info/WHEEL
pythondata_cpu_cva5-0.0.post649.dist-info/top_level.txt
pythondata_cpu_cva5-0.0.post649.dist-info/RECORD
