Metadata-Version: 2.1
Name: pythondata-cpu-cva5
Version: 0.0.post649
Summary: Python module containing system_verilog files for CVA5 cpu.
Home-page: https://github.com/litex-hub/pythondata-cpu-cva5
Author: LiteX Authors
Author-email: litex@googlegroups.com
Project-URL: Bug Tracker, https://github.com/litex-hub/pythondata-cpu-cva5/issues
Project-URL: Source Code, https://github.com/litex-hub/pythondata-cpu-cva5
Classifier: Programming Language :: Python :: 3
Classifier: License :: OSI Approved :: Apache Software License
Classifier: Operating System :: OS Independent
Requires-Python: >=3.5
License-File: LICENSE
